speech_interface/__init__.py
speech_interface/encoders.py
speech_interface/utils.py
speech_interface/interfaces/__init__.py
speech_interface/interfaces/hifi_gan.py
speech_interface/interfaces/mel_gan.py
speech_interface/interfaces/multiband_mel_gan.py
speech_interface/interfaces/stats.py
speech_interface/interfaces/waveglow.py
speech_interface/models/__init__.py
speech_interface/models/glow.py
speech_interface/models/hifi_gan.py
speech_interface-0.0.2.1.dist-info/LICENSE
speech_interface-0.0.2.1.dist-info/METADATA
speech_interface-0.0.2.1.dist-info/WHEEL
speech_interface-0.0.2.1.dist-info/top_level.txt
speech_interface-0.0.2.1.dist-info/RECORD
