Metadata-Version: 2.1
Name: speech-interface
Version: 0.0.2.1
Summary: An interface for neural speech synthesis with Pytorch
Home-page: https://github.com/AppleHolic/SpeechInterface
Author: ILJI CHOI
Author-email: choiilji@gmail.com
License: MIT
Keywords: speech
Platform: UNKNOWN
Classifier: Programming Language :: Python :: 3
Classifier: License :: OSI Approved :: MIT License
Requires-Python: >=3.6
Requires-Dist: torch (>=1.7.0)
Requires-Dist: gdown
Requires-Dist: librosa
Requires-Dist: requests
Requires-Dist: parallel-wavegan
